.gitignore
CHANGES.rst
MANIFEST.in
README.rst
README.txt
bootstrap.py
buildout.cfg
setup.py
docs/INSTALL.txt
docs/LICENSE.GPL
docs/LICENSE.txt
zest/__init__.py
zest.commentcleanup.egg-info/PKG-INFO
zest.commentcleanup.egg-info/SOURCES.txt
zest.commentcleanup.egg-info/dependency_links.txt
zest.commentcleanup.egg-info/entry_points.txt
zest.commentcleanup.egg-info/namespace_packages.txt
zest.commentcleanup.egg-info/not-zip-safe
zest.commentcleanup.egg-info/requires.txt
zest.commentcleanup.egg-info/top_level.txt
zest/commentcleanup/__init__.py
zest/commentcleanup/configure.zcml
zest/commentcleanup/details.pt
zest/commentcleanup/list.pt
zest/commentcleanup/overview.pt
zest/commentcleanup/views.py